malloryai/__init__.py
malloryai/sdk/__init__.py
malloryai/sdk/api/__init__.py
malloryai/sdk/api/v1/__init__.py
malloryai/sdk/api/v1/api.py
malloryai/sdk/api/v1/clients/__init__.py
malloryai/sdk/api/v1/clients/bulletins.py
malloryai/sdk/api/v1/clients/content_chunks.py
malloryai/sdk/api/v1/clients/detection_signatures.py
malloryai/sdk/api/v1/clients/exploitations.py
malloryai/sdk/api/v1/clients/exploits.py
malloryai/sdk/api/v1/clients/products.py
malloryai/sdk/api/v1/clients/references.py
malloryai/sdk/api/v1/clients/sources.py
malloryai/sdk/api/v1/clients/threat_actors.py
malloryai/sdk/api/v1/clients/vendors.py
malloryai/sdk/api/v1/clients/vulnerabilities.py
malloryai/sdk/api/v1/decorators/sorting.py
malloryai/sdk/api/v1/exceptions/__init__.py
malloryai/sdk/api/v1/exceptions/exception.py
malloryai/sdk/api/v1/exceptions/not_found.py
malloryai/sdk/api/v1/exceptions/validation.py
malloryai/sdk/api/v1/http_client.py
malloryai_sdk-0.3.2.dist-info/METADATA
malloryai_sdk-0.3.2.dist-info/WHEEL
malloryai_sdk-0.3.2.dist-info/entry_points.txt
malloryai_sdk-0.3.2.dist-info/RECORD
