Metadata-Version: 2.1
Name: malloryai-sdk
Version: 0.3.2
Summary: Official Python SDK for the MalloryAI platform providing seamless API integration
Author-Email: Mallory Team <hello@mallory.ai>
License: MIT
Project-URL: Homepage, https://github.com/malloryai/mallory-api-sdk
Project-URL: Documentation, https://github.com/malloryai/mallory-api-sdk#readme
Project-URL: Repository, https://github.com/malloryai/mallory-api-sdk.git
Project-URL: Issues, https://github.com/malloryai/mallory-api-sdk/issues
Requires-Python: >=3.9
Requires-Dist: aiohttp>=3.11.12
Requires-Dist: pydantic>=2.10.6
Requires-Dist: requests>=2.32.3
